mcompare/__init__.py
mcompare/classifiers_wrapper.py
mcompare/model_wrapper.py
mcompare/regressors_wrapper.py
mcompare-1.0.0.dist-info/LICENSE
mcompare-1.0.0.dist-info/METADATA
mcompare-1.0.0.dist-info/WHEEL
mcompare-1.0.0.dist-info/top_level.txt
mcompare-1.0.0.dist-info/RECORD
