Metadata-Version: 2.1
Name: mcompare
Version: 1.0.0
Summary: Wrapper for SKLearn Models
Home-page: https://github.com/abditimer/mcompare
Author: Abdi Timer
Author-email: thatimer@gmail.com
License: MIT
Platform: UNKNOWN
Classifier: Programming Language :: Python :: 3
Classifier: License :: OSI Approved :: MIT License
Classifier: Operating System :: OS Independent
Requires-Python: >=3.6
